LICENSE.txt
MANIFEST.in
README.rst
setup.py
jk_xmljsonconv/AbstractFormatConverter.py
jk_xmljsonconv/FormatConverter.py
jk_xmljsonconv/FormatConverterChain.py
jk_xmljsonconv/FormatConverterJson2JsonFile.py
jk_xmljsonconv/FormatConverterJson2JsonStr.py
jk_xmljsonconv/FormatConverterJson2XmlStr.py
jk_xmljsonconv/FormatConverterJsonFile2Json.py
jk_xmljsonconv/FormatConverterJsonFile2JsonStr.py
jk_xmljsonconv/FormatConverterJsonStr2Json.py
jk_xmljsonconv/FormatConverterXml2XmlFile.py
jk_xmljsonconv/FormatConverterXmlFile2Xml.py
jk_xmljsonconv/FormatConverterXmlFile2XmlStr.py
jk_xmljsonconv/FormatConverterXmlStr2Json.py
jk_xmljsonconv/FormatConverterXmlStr2Xml.py
jk_xmljsonconv/FormatConverterXmlStr2XmlFile.py
jk_xmljsonconv/__init__.py
jk_xmljsonconv.egg-info/PKG-INFO
jk_xmljsonconv.egg-info/SOURCES.txt
jk_xmljsonconv.egg-info/dependency_links.txt
jk_xmljsonconv.egg-info/not-zip-safe
jk_xmljsonconv.egg-info/requires.txt
jk_xmljsonconv.egg-info/top_level.txt