Metadata-Version: 1.1
Name: jk-xmljsonconv
Version: 0.2017.1.17
Summary: A python module to convert XML to JSON and the other way around through a conversion manager.
Home-page: https://github.com/jkpubsrc/python-module-jk-xmljsonconv
Author: Jürgen Knauth
Author-email: pubsrc@binary-overflow.de
License: Apache 2.0
Download-URL: https://github.com/jkpubsrc/python-module-jk-xmljsonconv/tarball/0.2017.1.17
Keywords: format-conversion,xml,json
Platform: UNKNOWN
Classifier: Development Status :: 4 - Beta
Classifier: Programming Language :: Python :: 3.5
Classifier: License :: OSI Approved :: Apache Software License
